eox_hooks/__init__.py
eox_hooks/actions.py
eox_hooks/actions_handler.py
eox_hooks/apps.py
eox_hooks/receivers.py
eox_hooks/serializers.py
eox_hooks/tasks.py
eox_hooks/urls.py
eox_hooks/utils.py
eox_hooks/views.py
eox_hooks/edxapp_wrapper/__init__.py
eox_hooks/edxapp_wrapper/course_modes.py
eox_hooks/edxapp_wrapper/courses.py
eox_hooks/edxapp_wrapper/enrollments.py
eox_hooks/edxapp_wrapper/models.py
eox_hooks/edxapp_wrapper/backends/__init__.py
eox_hooks/edxapp_wrapper/backends/course_modes_j_v1.py
eox_hooks/edxapp_wrapper/backends/course_modes_l_v1.py
eox_hooks/edxapp_wrapper/backends/course_modes_l_v1_test.py
eox_hooks/edxapp_wrapper/backends/courses_j_v1.py
eox_hooks/edxapp_wrapper/backends/courses_j_v1_test.py
eox_hooks/edxapp_wrapper/backends/courses_l_v1.py
eox_hooks/edxapp_wrapper/backends/courses_p_v1.py
eox_hooks/edxapp_wrapper/backends/enrollments_j_v1.py
eox_hooks/edxapp_wrapper/backends/enrollments_l_v1.py
eox_hooks/edxapp_wrapper/backends/enrollments_l_v1_test.py
eox_hooks/edxapp_wrapper/backends/models_j_v1.py
eox_hooks/edxapp_wrapper/backends/models_l_v1.py
eox_hooks/edxapp_wrapper/backends/models_l_v1_test.py
eox_hooks/edxapp_wrapper/tests/__init__.py
eox_hooks/edxapp_wrapper/tests/integration/__init__.py
eox_hooks/edxapp_wrapper/tests/integration/test_backends.py
eox_hooks/settings/__init__.py
eox_hooks/settings/common.py
eox_hooks/settings/production.py
eox_hooks/settings/test.py
eox_hooks/tests/__init__.py
eox_hooks/tests/test_actions.py
eox_hooks/tests/test_actions_handler.py
eox_hooks/tests/test_apps.py
eox_hooks/tests/test_receivers.py
eox_hooks/tests/test_serializers.py
eox_hooks/tests/test_tasks.py
eox_hooks/tests/test_utils.py
eox_hooks/tests/test_views.py
eox_hooks/tests/integration/__init__.py
eox_hooks/tests/integration/test_views.py
eox_hooks-8.3.1.dist-info/licenses/AUTHORS.txt
eox_hooks-8.3.1.dist-info/licenses/LICENSE.txt
eox_hooks-8.3.1.dist-info/METADATA
eox_hooks-8.3.1.dist-info/WHEEL
eox_hooks-8.3.1.dist-info/entry_points.txt
eox_hooks-8.3.1.dist-info/top_level.txt
eox_hooks-8.3.1.dist-info/RECORD
