Metadata-Version: 2.4
Name: eox-hooks
Version: 8.3.1
Summary: EoxHooks
Author: eduNEXT
Author-email: contact@edunext.co
License: AGPL
Classifier: Development Status :: 5 - Production/Stable
Classifier: Framework :: Django :: 4.2
Classifier: Framework :: Django :: 5.2
Classifier: Intended Audience :: Developers
Classifier: License :: OSI Approved :: GNU Affero General Public License v3
Classifier: Operating System :: OS Independent
Classifier: Programming Language :: Python :: 3.11
Classifier: Programming Language :: Python :: 3.12
License-File: LICENSE.txt
License-File: AUTHORS.txt
Requires-Dist: celery
Requires-Dist: openedx-events
Requires-Dist: djangorestframework
Requires-Dist: edx-opaque-keys[django]
Requires-Dist: Django
Requires-Dist: django-crum
Dynamic: author
Dynamic: author-email
Dynamic: classifier
Dynamic: description
Dynamic: description-content-type
Dynamic: license
Dynamic: license-file
Dynamic: requires-dist
Dynamic: summary
